odoo/addons/stock_move_packaging_qty/README.rst
odoo/addons/stock_move_packaging_qty/__init__.py
odoo/addons/stock_move_packaging_qty/__manifest__.py
odoo/addons/stock_move_packaging_qty/i18n/stock_move_packaging_qty.pot
odoo/addons/stock_move_packaging_qty/models/__init__.py
odoo/addons/stock_move_packaging_qty/models/stock_move.py
odoo/addons/stock_move_packaging_qty/readme/CONTRIBUTORS.rst
odoo/addons/stock_move_packaging_qty/readme/DESCRIPTION.rst
odoo/addons/stock_move_packaging_qty/static/description/icon.png
odoo/addons/stock_move_packaging_qty/static/description/index.html
odoo/addons/stock_move_packaging_qty/tests/__init__.py
odoo/addons/stock_move_packaging_qty/tests/test_stock_move_packaging_qty.py
odoo/addons/stock_move_packaging_qty/views/stock_move_tree_view.xml
odoo/addons/stock_move_packaging_qty/views/stock_picking_form_view.xml
odoo13_addon_stock_move_packaging_qty-13.0.1.1.1.dist-info/METADATA
odoo13_addon_stock_move_packaging_qty-13.0.1.1.1.dist-info/WHEEL
odoo13_addon_stock_move_packaging_qty-13.0.1.1.1.dist-info/top_level.txt
odoo13_addon_stock_move_packaging_qty-13.0.1.1.1.dist-info/RECORD
